<?xml version="1.0" encoding="utf-8"?>
<resources name="en" flag="gb" title="English">
    <string name="_bx_github"><![CDATA[GitHub]]></string>

    <string name="_bx_github_option_authorize"><![CDATA[Authorize using]]></string>
    <string name="_bx_github_option_authorize_pat"><![CDATA[Personal access token (PAT)]]></string>
    <string name="_bx_github_option_authorize_app"><![CDATA[Login with GitHub (APP)]]></string>

    <string name="_bx_github_form_apps"><![CDATA[Apps]]></string>
    <string name="_bx_github_form_apps_display_add"><![CDATA[Add apps]]></string>
    <string name="_bx_github_form_apps_display_edit"><![CDATA[Edit apps]]></string>
    <string name="_bx_github_form_apps_input_sys_title"><![CDATA[Title]]></string>
    <string name="_bx_github_form_apps_input_title"><![CDATA[Title]]></string>
    <string name="_bx_github_form_apps_input_sys_client_id"><![CDATA[Client ID]]></string>
    <string name="_bx_github_form_apps_input_client_id"><![CDATA[Client ID]]></string>
    <string name="_bx_github_form_apps_input_sys_client_secret"><![CDATA[Client Secret]]></string>
    <string name="_bx_github_form_apps_input_client_secret"><![CDATA[Client Secret]]></string>
    <string name="_bx_github_form_apps_input_sys_do_submit"><![CDATA[Submit]]></string>
    <string name="_bx_github_form_apps_input_do_submit"><![CDATA[Submit]]></string>

    <string name="_bx_github_form_settings"><![CDATA[Settings]]></string>
    <string name="_bx_github_form_settings_display_edit"><![CDATA[Edit settings]]></string>
    <string name="_bx_github_form_settings_input_sys_pat"><![CDATA[Access token]]></string>
    <string name="_bx_github_form_settings_input_pat"><![CDATA[Access token]]></string>
    <string name="_bx_github_form_settings_input_sys_do_submit"><![CDATA[Submit]]></string>
    <string name="_bx_github_form_settings_input_do_submit"><![CDATA[Submit]]></string>
    <string name="_bx_github_form_input_err_enter"><![CDATA[This field is essential. Please, enter a value.]]></string>

    <string name="_bx_github_page_title_sys_settings"><![CDATA[Settings]]></string>
    <string name="_bx_github_page_title_settings"><![CDATA[GitHub Settings]]></string>
    <string name="_bx_github_page_block_title_apps"><![CDATA[GitHub Apps for repository provider]]></string>
    <string name="_bx_github_page_block_title_authorizations"><![CDATA[GitHub Apps' authorizations for repository user]]></string>
    <string name="_bx_github_page_block_title_settings"><![CDATA[GitHub Settings for repository user]]></string>
    <string name="_bx_github_page_title_sys_authorize"><![CDATA[Authorize]]></string>
    <string name="_bx_github_page_title_authorize"><![CDATA[GitHub Authorize]]></string>
    <string name="_bx_github_page_block_title_authorize"><![CDATA[GitHub Authorize]]></string>

    <string name="_bx_github_menu_item_title_system_settings"><![CDATA[GitHub Settings]]></string>
    <string name="_bx_github_menu_item_title_settings"><![CDATA[GitHub]]></string>

    <string name="_bx_github_grid_column_title_apps_title"><![CDATA[Title]]></string>
    <string name="_bx_github_grid_column_title_apps_client_id"><![CDATA[Client ID]]></string>
    <string name="_bx_github_grid_column_title_apps_callback_url"><![CDATA[Callback URL]]></string>
    <string name="_bx_github_grid_action_title_apps_add"><![CDATA[Add]]></string>
    <string name="_bx_github_grid_action_title_apps_edit"><![CDATA[Edit]]></string>
    <string name="_bx_github_grid_action_title_apps_delete"><![CDATA[Delete]]></string>
    <string name="_bx_github_grid_popup_title_apps_add"><![CDATA[Add App]]></string>
    <string name="_bx_github_grid_popup_title_apps_edit"><![CDATA[Edit App]]></string>

    <string name="_bx_github_grid_column_title_auth_app_id"><![CDATA[GitHub App]]></string>
    <string name="_bx_github_grid_column_title_auth_added"><![CDATA[Added]]></string>
    <string name="_bx_github_grid_column_title_auth_changed"><![CDATA[Changed]]></string>
    <string name="_bx_github_grid_column_title_auth_at_expires_in"><![CDATA[Expires in]]></string>
    <string name="_bx_github_grid_action_title_apps_refresh"><![CDATA[Refresh access token]]></string>
    <string name="_bx_github_grid_action_title_auth_delete"><![CDATA[Delete]]></string>

    <string name="_bx_github_acl_action_add_app"><![CDATA[Add GitHub app]]></string>

    <string name="_bx_github_log_api"><![CDATA[GitHub API Logs]]></string>

    <string name="_bx_github_msg_save_settings"><![CDATA[Settings were successfully saved.]]></string>
    <string name="_bx_github_err_save_settings"><![CDATA[Cannot save settings.]]></string>
    <string name="_bx_github_err_cannot_perform_action"><![CDATA[An error appeared. Please report.]]></string>

    <string name="_bx_github_txt_login"><![CDATA[Login with GitHub]]></string>
    <string name="_bx_github_txt_authorized"><![CDATA[Authorized]]></string>
    <string name="_bx_github_txt_manage_here"><![CDATA[Manage your authorizations here:]]></string>
    <string name="_bx_github_txt_settings"><![CDATA[GitHub settings]]></string>
</resources>
